txt2txt/__init__.py
txt2txt/txt2txt.py
txt2txt-1.1.2.dist-info/LICENSE
txt2txt-1.1.2.dist-info/METADATA
txt2txt-1.1.2.dist-info/WHEEL
txt2txt-1.1.2.dist-info/top_level.txt
txt2txt-1.1.2.dist-info/RECORD
